appy/__init__.py
appy/__version__.py
appy/ast_utils.py
appy/config.py
appy/jit.py
appy/utils.py
appy/codegen/__init__.py
appy/codegen/typesys.py
appy/codegen/high_level_transforms/__init__.py
appy/codegen/high_level_transforms/add_dim_to_slice.py
appy/codegen/high_level_transforms/add_entry_exit_data_transfer.py
appy/codegen/high_level_transforms/attach_mask_info.py
appy/codegen/high_level_transforms/aug_assign_rewriter.py
appy/codegen/high_level_transforms/block_loop.py
appy/codegen/high_level_transforms/check_for_assign_pragma.py
appy/codegen/high_level_transforms/convert_pragma_seq_for.py
appy/codegen/high_level_transforms/get_loaded_names.py
appy/codegen/high_level_transforms/hoist_acc.py
appy/codegen/high_level_transforms/insert_barrier.py
appy/codegen/high_level_transforms/insert_before_loop.py
appy/codegen/high_level_transforms/insert_initialization.py
appy/codegen/high_level_transforms/link_pragma.py
appy/codegen/high_level_transforms/process_data_pragma.py
appy/codegen/high_level_transforms/process_reduction_pragma.py
appy/codegen/high_level_transforms/range_rewriter.py
appy/codegen/high_level_transforms/rewrite_call.py
appy/codegen/high_level_transforms/select_num_warps.py
appy/codegen/high_level_transforms/ternary_to_where.py
appy/codegen/high_level_transforms/transform_tensor_pragma.py
appy/codegen/high_level_transforms/utils.py
appy/codegen/triton/__init__.py
appy/codegen/triton/gen_code.py
appy/codegen/triton/gen_device_code.py
appy/codegen/triton/gen_host_code.py
appyc-0.2.0.dist-info/LICENSE
appyc-0.2.0.dist-info/METADATA
appyc-0.2.0.dist-info/WHEEL
appyc-0.2.0.dist-info/top_level.txt
appyc-0.2.0.dist-info/RECORD
