Metadata-Version: 2.1
Name: appyc
Version: 0.2.0
Summary: APPy (Annotated Parallelism for Python) enables users to annotate loops and tensor expressions in Python with compiler directives akin to OpenMP, and automatically compiles the annotated code to GPU kernels.
Home-page: https://github.com/habanero-lab/APPy
Author: Tong Zhou
Author-email: zt9465@gmail.com
Classifier: Programming Language :: Python :: 3
Classifier: License :: OSI Approved :: MIT License
Classifier: Operating System :: OS Independent
Requires-Python: >=3.9
License-File: LICENSE
Requires-Dist: ast-comments
Requires-Dist: black
Requires-Dist: sympy
Requires-Dist: ast-transforms
